treepruner/__init__.py
treepruner/src/__init__.py
treepruner/src/tree_data.py
treepruner/src/treepruner.py
treepruner/src/utils.py
treepruner/test/__init__.py
treepruner/test/test_treepruner.py
treepruner-1.0.3.dist-info/LICENSE.txt
treepruner-1.0.3.dist-info/METADATA
treepruner-1.0.3.dist-info/WHEEL
treepruner-1.0.3.dist-info/top_level.txt
treepruner-1.0.3.dist-info/RECORD
