Metadata-Version: 2.2
Name: treepruner
Version: 1.0.3
Summary: A package for pruning phylogenetic trees
Home-page: https://github.com/hegedani/Pruning_algorithms_for_phylogenetic_trees
Author: Dániel Hegedűs, Márk Hunor Juhász
Author-email: markh.shepherd@gmail.com
License: MIT
Classifier: License :: OSI Approved :: MIT License
Classifier: Programming Language :: Python :: 3.10
Classifier: Operating System :: OS Independent
Requires-Python: >=3.10, <3.13
License-File: LICENSE.txt
Requires-Dist: ete3>=3.1.3
Requires-Dist: numpy>=2.2.3
Requires-Dist: matplotlib>=3.10.0
Requires-Dist: six>=1.17.0
Provides-Extra: dev
Requires-Dist: pytest>=7.0; extra == "dev"
Requires-Dist: twine>=4.0.2; extra == "dev"
Dynamic: author
Dynamic: author-email
Dynamic: classifier
Dynamic: description
Dynamic: description-content-type
Dynamic: home-page
Dynamic: license
Dynamic: provides-extra
Dynamic: requires-dist
Dynamic: requires-python
Dynamic: summary
